fido_u2f/__init__.py
fido_u2f/_typing.py
fido_u2f/constants.py
fido_u2f/device.py
fido_u2f/enums.py
fido_u2f/exceptions.py
fido_u2f/registration.py
fido_u2f/utils.py
fido_u2f/verification.py
fido_u2f/sample/__init__.py
fido_u2f/sample/flask.py
fido_u2f/sample/tables.py
fido_u2f/tests/__init__.py
fido_u2f/tests/test_response_parse_validate.py
fido_u2f/tests/test_utils.py
py_fido-0.4.0.dist-info/METADATA
py_fido-0.4.0.dist-info/RECORD
py_fido-0.4.0.dist-info/WHEEL
py_fido-0.4.0.dist-info/top_level.txt
