Metadata-Version: 2.1
Name: py-fido
Version: 0.4.0
Summary: A framework-agnostic implementation of the FIDO U2F server workflow
Home-page: https://github.com/leesdolphin/py-fido/
Author: Opal Symes
Author-email: code@opal.codes
License: UNKNOWN
Platform: UNKNOWN
Classifier: Development Status :: 3 - Alpha
Classifier: Intended Audience :: Developers
Classifier: License :: OSI Approved :: GNU Lesser General Public License v3 or later (LGPLv3+)
Classifier: Natural Language :: English
Classifier: Operating System :: OS Independent
Classifier: Programming Language :: Python
Classifier: Programming Language :: Python :: 3
Classifier: Programming Language :: Python :: 3 :: Only
Classifier: Programming Language :: Python :: 3.5
Classifier: Programming Language :: Python :: 3.6
Classifier: Programming Language :: Python :: 3.7
Classifier: Topic :: Security
Provides-Extra: sample
Requires-Dist: cryptography (<3,>=2.3)
Provides-Extra: sample
Requires-Dist: flask; extra == 'sample'
Requires-Dist: Flask-SQLAlchemy; extra == 'sample'
